{
  "version": "7",
  "dialect": "mysql",
  "entries": [
    {
      "idx": 0,
      "version": "5",
      "when": 1775480554853,
      "tag": "0000_acoustic_orphan",
      "breakpoints": true
    },
    {
      "idx": 1,
      "version": "5",
      "when": 1775493272948,
      "tag": "0001_new_red_skull",
      "breakpoints": true
    },
    {
      "idx": 2,
      "version": "5",
      "when": 1775511623519,
      "tag": "0002_fixed_vulture",
      "breakpoints": true
    },
    {
      "idx": 3,
      "version": "5",
      "when": 1775577819529,
      "tag": "0003_nasty_salo",
      "breakpoints": true
    },
    {
      "idx": 4,
      "version": "5",
      "when": 1775578869155,
      "tag": "0004_productive_master_chief",
      "breakpoints": true
    },
    {
      "idx": 5,
      "version": "5",
      "when": 1775859397018,
      "tag": "0005_quick_wildside",
      "breakpoints": true
    }
  ]
}